Metadata-Version: 2.1
Name: orbis-plugin-aggregation-babelfly
Version: 2.3.0
Summary: The Babelfly aggregation plugin for Orbis
Home-page: https://github.com/orbis-eval/orbis_plugin_aggregation_babelfly
Author: fabod
License: GPL2
Platform: UNKNOWN
Requires-Python: >3.6
Requires-Dist: requests (>=2.20.0)
